Metadata-Version: 2.1
Name: desalsim
Version: 1.1.1
Home-page: https://github.com/rodoulak/desalsim.git
Author: rodoulak
Author-email: r.ktori@tudelft.nl
License: MIT
License-File: LICENSE
Requires-Dist: numpy
Requires-Dist: pandas
Requires-Dist: scipy
Requires-Dist: matplotlib
Requires-Dist: scikit-learn
Requires-Dist: plotly
Requires-Dist: openpyxl
